msgpack_numpy.py
msgpack_numpy-0.4.8.dist-info/AUTHORS.md
msgpack_numpy-0.4.8.dist-info/LICENSE.md
msgpack_numpy-0.4.8.dist-info/METADATA
msgpack_numpy-0.4.8.dist-info/WHEEL
msgpack_numpy-0.4.8.dist-info/top_level.txt
msgpack_numpy-0.4.8.dist-info/RECORD
